{"referralId":{"0":"e-0-4be0a6cf4f15c92829f6cb0b-0"},"reasons.count":{"0":0},"reasons.items":{"0":[{"summary":"This spot is popular","type":"general","reasonName":"globalInteractionReason"}]},"venue.id":{"0":"4be0a6cf4f15c92829f6cb0b"},"venue.name":{"0":"Woodford Park"},"venue.location.lat":{"0":43.6331524975},"venue.location.lng":{"0":-79.496265811},"venue.location.labeledLatLngs":{"0":[{"label":"display","lat":43.6331524975,"lng":-79.496265811}]},"venue.location.distance":{"0":390},"venue.location.cc":{"0":"CA"},"venue.location.country":{"0":"Canada"},"venue.location.formattedAddress":{"0":["Canada"]},"venue.categories":{"0":[{"id":"4bf58dd8d48988d1e8941735","name":"Baseball Field","pluralName":"Baseball Fields","shortName":"Baseball Field","icon":{"prefix":"https:\/\/ss3.4sqi.net\/img\/categories_v2\/parks_outdoors\/baseballfield_","suffix":".png"},"primary":true}]},"venue.photos.count":{"0":0},"venue.photos.groups":{"0":[]}}