{"referralId":{"0":"e-0-4ad9dce6f964a520651b21e3-0","1":"e-0-4e1fad69fa761d67106a9989-1","2":"e-0-5331a799498e3bfbae4a5a04-2","3":"e-0-4c64ca1b772bef3bfadbc2aa-3"},"reasons.count":{"0":0,"1":0,"2":0,"3":0},"reasons.items":{"0":[{"summary":"This spot is popular","type":"general","reasonName":"globalInteractionReason"}],"1":[{"summary":"This spot is popular","type":"general","reasonName":"globalInteractionReason"}],"2":[{"summary":"This spot is popular","type":"general","reasonName":"globalInteractionReason"}],"3":[{"summary":"This spot is popular","type":"general","reasonName":"globalInteractionReason"}]},"venue.id":{"0":"4ad9dce6f964a520651b21e3","1":"4e1fad69fa761d67106a9989","2":"5331a799498e3bfbae4a5a04","3":"4c64ca1b772bef3bfadbc2aa"},"venue.name":{"0":"Eagle's Nest Golf Club","1":"AY Jackson Pool","2":"Villa Madina","3":"Duncan Creek Park"},"venue.location.address":{"0":"10000 Dufferin Rd","1":"50 Francine drive","2":null,"3":"Aspenwood Drive"},"venue.location.lat":{"0":43.805454826,"1":43.8045154137,"2":43.8016850623,"3":43.8055392882},"venue.location.lng":{"0":-79.3641859224,"1":-79.3661382158,"2":-79.3639384457,"3":-79.3606945694},"venue.location.labeledLatLngs":{"0":[{"label":"display","lat":43.805454826,"lng":-79.3641859224}],"1":[{"label":"display","lat":43.8045154137,"lng":-79.3661382158}],"2":[{"label":"display","lat":43.8016850623,"lng":-79.3639384457}],"3":[{"label":"display","lat":43.8055392882,"lng":-79.3606945694}]},"venue.location.distance":{"0":197,"1":231,"2":234,"3":296},"venue.location.cc":{"0":"CA","1":"CA","2":"CA","3":"CA"},"venue.location.city":{"0":"Toronto","1":"North York","2":"Toronto","3":"Toronto"},"venue.location.state":{"0":"ON","1":"ON","2":"ON","3":"ON"},"venue.location.country":{"0":"Canada","1":"Canada","2":"Canada","3":"Canada"},"venue.location.formattedAddress":{"0":["10000 Dufferin Rd","Toronto ON","Canada"],"1":["50 Francine drive (Leslie)","North York ON","Canada"],"2":["Toronto ON","Canada"],"3":["Aspenwood Drive (btwn Don Mills & Leslie)","Toronto ON","Canada"]},"venue.categories":{"0":[{"id":"4bf58dd8d48988d1e6941735","name":"Golf Course","pluralName":"Golf Courses","shortName":"Golf Course","icon":{"prefix":"https:\/\/ss3.4sqi.net\/img\/categories_v2\/parks_outdoors\/golfcourse_","suffix":".png"},"primary":true}],"1":[{"id":"4bf58dd8d48988d15e941735","name":"Pool","pluralName":"Pools","shortName":"Pool","icon":{"prefix":"https:\/\/ss3.4sqi.net\/img\/categories_v2\/parks_outdoors\/pool_","suffix":".png"},"primary":true}],"2":[{"id":"4bf58dd8d48988d1c0941735","name":"Mediterranean Restaurant","pluralName":"Mediterranean Restaurants","shortName":"Mediterranean","icon":{"prefix":"https:\/\/ss3.4sqi.net\/img\/categories_v2\/food\/mediterranean_","suffix":".png"},"primary":true}],"3":[{"id":"4bf58dd8d48988d1e5941735","name":"Dog Run","pluralName":"Dog Runs","shortName":"Dog Run","icon":{"prefix":"https:\/\/ss3.4sqi.net\/img\/categories_v2\/parks_outdoors\/dogrun_","suffix":".png"},"primary":true}]},"venue.photos.count":{"0":0,"1":0,"2":0,"3":0},"venue.photos.groups":{"0":[],"1":[],"2":[],"3":[]},"venue.location.crossStreet":{"0":null,"1":"Leslie","2":null,"3":"btwn Don Mills & Leslie"}}