{"referralId":{"0":"e-0-4b0aed06f964a520202a23e3-0","1":"e-0-50c3ae15e4b08c3b596c6069-1","2":"e-0-4c18e819d4d9c9284e19f029-2","3":"e-0-4b639286f964a5203c842ae3-3","4":"e-0-57e7d6bd498e0d78f21a4169-4"},"reasons.count":{"0":0,"1":0,"2":0,"3":0,"4":0},"reasons.items":{"0":[{"summary":"This spot is popular","type":"general","reasonName":"globalInteractionReason"}],"1":[{"summary":"This spot is popular","type":"general","reasonName":"globalInteractionReason"}],"2":[{"summary":"This spot is popular","type":"general","reasonName":"globalInteractionReason"}],"3":[{"summary":"This spot is popular","type":"general","reasonName":"globalInteractionReason"}],"4":[{"summary":"This spot is popular","type":"general","reasonName":"globalInteractionReason"}]},"venue.id":{"0":"4b0aed06f964a520202a23e3","1":"50c3ae15e4b08c3b596c6069","2":"4c18e819d4d9c9284e19f029","3":"4b639286f964a5203c842ae3","4":"57e7d6bd498e0d78f21a4169"},"venue.name":{"0":"Island Foods","1":"Baretto Caff\u00e9","2":"LA Fitness","3":"Gonoe Sushi","4":"Elite Basketball Camps"},"venue.location.address":{"0":"1310 Don Mills Rd.","1":"1262 Don Mills Rd","2":"1380 Don Mills Road","3":"1310 Don Mills Rd, Unit 1","4":"B-20 Scarsdale Road"},"venue.location.lat":{"0":43.745866074,"1":43.7444564635,"2":43.7476652289,"3":43.7457368196,"4":43.748789728},"venue.location.lng":{"0":-79.3460353332,"1":-79.3464597847,"2":-79.3470769607,"3":-79.3459911992,"4":-79.35422793},"venue.location.labeledLatLngs":{"0":[{"label":"display","lat":43.745866074,"lng":-79.3460353332}],"1":[{"label":"display","lat":43.7444564635,"lng":-79.3464597847}],"2":[{"label":"display","lat":43.7476652289,"lng":-79.3470769607}],"3":[{"label":"display","lat":43.7457368196,"lng":-79.3459911992}],"4":[{"label":"display","lat":43.748789728,"lng":-79.35422793}]},"venue.location.distance":{"0":494,"1":488,"2":455,"3":498,"4":360},"venue.location.cc":{"0":"CA","1":"CA","2":"CA","3":"CA","4":"CA"},"venue.location.city":{"0":"Toronto","1":"Toronto","2":"Toronto","3":"Toronto","4":"Toronto"},"venue.location.state":{"0":"ON","1":"ON","2":"ON","3":"ON","4":"ON"},"venue.location.country":{"0":"Canada","1":"Canada","2":"Canada","3":"Canada","4":"Canada"},"venue.location.formattedAddress":{"0":["1310 Don Mills Rd.","Toronto ON","Canada"],"1":["1262 Don Mills Rd","Toronto ON","Canada"],"2":["1380 Don Mills Road (Mallard Rd)","Toronto ON M3B 2X2","Canada"],"3":["1310 Don Mills Rd, Unit 1 (at Bond Ave.)","Toronto ON M3B 2W6","Canada"],"4":["B-20 Scarsdale Road","Toronto ON M3B 2R2","Canada"]},"venue.categories":{"0":[{"id":"4bf58dd8d48988d144941735","name":"Caribbean Restaurant","pluralName":"Caribbean Restaurants","shortName":"Caribbean","icon":{"prefix":"https:\/\/ss3.4sqi.net\/img\/categories_v2\/food\/caribbean_","suffix":".png"},"primary":true}],"1":[{"id":"4bf58dd8d48988d16d941735","name":"Caf\u00e9","pluralName":"Caf\u00e9s","shortName":"Caf\u00e9","icon":{"prefix":"https:\/\/ss3.4sqi.net\/img\/categories_v2\/food\/cafe_","suffix":".png"},"primary":true}],"2":[{"id":"4bf58dd8d48988d175941735","name":"Gym \/ Fitness Center","pluralName":"Gyms or Fitness Centers","shortName":"Gym \/ Fitness","icon":{"prefix":"https:\/\/ss3.4sqi.net\/img\/categories_v2\/building\/gym_","suffix":".png"},"primary":true}],"3":[{"id":"4bf58dd8d48988d111941735","name":"Japanese Restaurant","pluralName":"Japanese Restaurants","shortName":"Japanese","icon":{"prefix":"https:\/\/ss3.4sqi.net\/img\/categories_v2\/food\/japanese_","suffix":".png"},"primary":true}],"4":[{"id":"4f4528bc4b90abdf24c9de85","name":"Athletics & Sports","pluralName":"Athletics & Sports","shortName":"Athletics & Sports","icon":{"prefix":"https:\/\/ss3.4sqi.net\/img\/categories_v2\/shops\/sports_outdoors_","suffix":".png"},"primary":true}]},"venue.photos.count":{"0":0,"1":0,"2":0,"3":0,"4":0},"venue.photos.groups":{"0":[],"1":[],"2":[],"3":[],"4":[]},"venue.location.crossStreet":{"0":null,"1":null,"2":"Mallard Rd","3":"at Bond Ave.","4":null},"venue.location.postalCode":{"0":null,"1":null,"2":"M3B 2X2","3":"M3B 2W6","4":"M3B 2R2"}}